dis_snek/__init__.py
dis_snek/py.typed
dis_snek/api/__init__.py
dis_snek/api/events/__init__.py
dis_snek/api/events/discord.py
dis_snek/api/events/internal.py
dis_snek/api/events/processors/__init__.py
dis_snek/api/events/processors/_template.py
dis_snek/api/events/processors/channel_events.py
dis_snek/api/events/processors/guild_events.py
dis_snek/api/events/processors/member_events.py
dis_snek/api/events/processors/message_events.py
dis_snek/api/events/processors/reaction_events.py
dis_snek/api/events/processors/role_events.py
dis_snek/api/events/processors/stage_events.py
dis_snek/api/events/processors/thread_events.py
dis_snek/api/events/processors/user_events.py
dis_snek/api/events/processors/voice_events.py
dis_snek/api/gateway/__init__.py
dis_snek/api/gateway/gateway.py
dis_snek/api/gateway/state.py
dis_snek/api/gateway/websocket.py
dis_snek/api/http/__init__.py
dis_snek/api/http/http_client.py
dis_snek/api/http/route.py
dis_snek/api/http/http_requests/__init__.py
dis_snek/api/http/http_requests/bot.py
dis_snek/api/http/http_requests/channels.py
dis_snek/api/http/http_requests/emojis.py
dis_snek/api/http/http_requests/guild.py
dis_snek/api/http/http_requests/interactions.py
dis_snek/api/http/http_requests/members.py
dis_snek/api/http/http_requests/messages.py
dis_snek/api/http/http_requests/reactions.py
dis_snek/api/http/http_requests/scheduled_events.py
dis_snek/api/http/http_requests/stickers.py
dis_snek/api/http/http_requests/threads.py
dis_snek/api/http/http_requests/users.py
dis_snek/api/http/http_requests/webhooks.py
dis_snek/api/voice/__init__.py
dis_snek/api/voice/audio.py
dis_snek/api/voice/encryption.py
dis_snek/api/voice/opus.py
dis_snek/api/voice/player.py
dis_snek/api/voice/voice_gateway.py
dis_snek/bin/opus-x64.dll
dis_snek/bin/opus-x86.dll
dis_snek/client/__init__.py
dis_snek/client/client.py
dis_snek/client/const.py
dis_snek/client/errors.py
dis_snek/client/smart_cache.py
dis_snek/client/mixins/__init__.py
dis_snek/client/mixins/send.py
dis_snek-9.0.0.dist-info/LICENSE
dis_snek-9.0.0.dist-info/METADATA
dis_snek-9.0.0.dist-info/WHEEL
dis_snek-9.0.0.dist-info/top_level.txt
dis_snek-9.0.0.dist-info/RECORD
