Metadata-Version: 2.1
Name: dis-snek
Version: 9.0.0
Summary: An API wrapper for Discord filled with snakes
Home-page: https://github.com/Discord-Snake-Pit/Dis-Snek
Author: LordOfPolls
Author-email: snekcord@gmail.com
License: UNKNOWN
Project-URL: Discord, https://discord.gg/dis-snek
Project-URL: Documentation, https://dis-snek.readthedocs.io
Project-URL: Trello Board, https://trello.com/b/LVjnmYKt/dev-board
Platform: UNKNOWN
Classifier: Development Status :: 3 - Alpha
Classifier: Framework :: AsyncIO
Classifier: Framework :: aiohttp
Classifier: Intended Audience :: Developers
Classifier: License :: OSI Approved :: MIT License
Classifier: Natural Language :: English
Classifier: Operating System :: OS Independent
Classifier: Programming Language :: Python :: 3
Classifier: Programming Language :: Python :: 3.10
Classifier: Topic :: Software Development :: Libraries
Classifier: Topic :: Software Development :: Libraries :: Python Modules
Classifier: Topic :: Documentation
Classifier: Typing :: Typed
Requires-Python: >=3.10
License-File: LICENSE
Requires-Dist: aiohttp
Requires-Dist: attrs
Requires-Dist: discord-typings
Requires-Dist: tomli
Provides-Extra: all
Requires-Dist: PyNaCl (<1.6,>=1.5.0) ; extra == 'all'
Requires-Dist: cchardet ; extra == 'all'
Requires-Dist: aiodns ; extra == 'all'
Requires-Dist: orjson ; extra == 'all'
Provides-Extra: speedup
Requires-Dist: cchardet ; extra == 'speedup'
Requires-Dist: aiodns ; extra == 'speedup'
Requires-Dist: orjson ; extra == 'speedup'
Provides-Extra: voice
Requires-Dist: PyNaCl (<1.6,>=1.5.0) ; extra == 'voice'
